pdfbookmarker.py
pdfbookmarker-0.6.0.dist-info/DESCRIPTION.rst
pdfbookmarker-0.6.0.dist-info/METADATA
pdfbookmarker-0.6.0.dist-info/RECORD
pdfbookmarker-0.6.0.dist-info/WHEEL
pdfbookmarker-0.6.0.dist-info/entry_points.txt
pdfbookmarker-0.6.0.dist-info/metadata.json
pdfbookmarker-0.6.0.dist-info/top_level.txt
