Metadata-Version: 2.0
Name: pdfbookmarker
Version: 0.6.0
Summary: Add bookmarks to existing PDF files
Home-page: https://github.com/RussellLuo/pdfbookmarker
Author: RussellLuo
Author-email: luopeng.he@gmail.com
License: MIT
Keywords: PDF,Bookmarks,Python tools
Platform: UNKNOWN
Requires-Dist: PyPDF2 (==1.26.0)
